sm_bluesky/__init__.py
sm_bluesky/__main__.py
sm_bluesky/_version.py
sm_bluesky/log.py
sm_bluesky/beamlines/__init__.py
sm_bluesky/beamlines/i10/__init__.py
sm_bluesky/beamlines/i10/configuration/default_setting.py
sm_bluesky/beamlines/i10/plans/__init__.py
sm_bluesky/beamlines/i10/plans/align_slits.py
sm_bluesky/beamlines/i10/plans/centre_direct_beam.py
sm_bluesky/beamlines/i10/plans/open_beam_path.py
sm_bluesky/beamlines/p99/__init__.py
sm_bluesky/beamlines/p99/helper/__init__.py
sm_bluesky/beamlines/p99/plans/__init__.py
sm_bluesky/common/__init__.py
sm_bluesky/common/helper/__init__.py
sm_bluesky/common/helper/add_meta.py
sm_bluesky/common/math_functions/__init__.py
sm_bluesky/common/math_functions/conversion.py
sm_bluesky/common/plan_stubs/__init__.py
sm_bluesky/common/plan_stubs/detectors.py
sm_bluesky/common/plan_stubs/motions.py
sm_bluesky/common/plan_stubs/set_and_do_other_plan.py
sm_bluesky/common/plans/__init__.py
sm_bluesky/common/plans/ad_plans.py
sm_bluesky/common/plans/alignments.py
sm_bluesky/common/plans/fast_scan.py
sm_bluesky/common/plans/grid_scan.py
sm_bluesky/electron_analyser/__init__.py
sm_bluesky/electron_analyser/plan_stubs/__init__.py
sm_bluesky/electron_analyser/plan_stubs/analyser_per_step.py
sm_bluesky/electron_analyser/plans/__init__.py
sm_bluesky/electron_analyser/plans/analyser_scans.py
sm_bluesky-1.0.0.dist-info/licenses/LICENSE
yaml_config/blueapi_config.yaml
sm_bluesky-1.0.0.dist-info/METADATA
sm_bluesky-1.0.0.dist-info/WHEEL
sm_bluesky-1.0.0.dist-info/entry_points.txt
sm_bluesky-1.0.0.dist-info/top_level.txt
sm_bluesky-1.0.0.dist-info/RECORD
