Metadata-Version: 2.4
Name: sm_bluesky
Version: 1.0.0
Summary: Bluesky code for Diamond's surface and magnetic materials beamline.
Author-email: Raymond Fan <raymond.fan@diamond.ac.uk>
License:                                  Apache License
Project-URL: GitHub, https://github.com/DiamondLightSource/sm-bluesky
Classifier: Development Status :: 3 - Alpha
Classifier: License :: OSI Approved :: Apache Software License
Classifier: Programming Language :: Python :: 3.11
Classifier: Programming Language :: Python :: 3.12
Classifier: Programming Language :: Python :: 3.13
Requires-Python: >=3.11
License-File: LICENSE
Requires-Dist: bluesky
Requires-Dist: dls-dodal>=1.59.1
Requires-Dist: ophyd-async[sim]
Requires-Dist: scanspec
Provides-Extra: dev
Requires-Dist: copier; extra == "dev"
Requires-Dist: myst-parser; extra == "dev"
Requires-Dist: pipdeptree; extra == "dev"
Requires-Dist: pre-commit; extra == "dev"
Requires-Dist: pydata-sphinx-theme>=0.12; extra == "dev"
Requires-Dist: pyright; extra == "dev"
Requires-Dist: pytest; extra == "dev"
Requires-Dist: pytest-cov; extra == "dev"
Requires-Dist: ruff; extra == "dev"
Requires-Dist: sphinx-autobuild; extra == "dev"
Requires-Dist: sphinx-copybutton; extra == "dev"
Requires-Dist: sphinx-design; extra == "dev"
Requires-Dist: tox-direct; extra == "dev"
Requires-Dist: types-mock; extra == "dev"
Requires-Dist: pytest-asyncio; extra == "dev"
Requires-Dist: jupyter; extra == "dev"
Requires-Dist: ipython; extra == "dev"
Requires-Dist: matplotlib; extra == "dev"
Requires-Dist: numpy; extra == "dev"
Requires-Dist: pyepics; extra == "dev"
Requires-Dist: blueapi; extra == "dev"
Dynamic: license-file
